sql_rewriter/__init__.py
sql_rewriter/parser.py
sql_rewriter/_generated/HiveLexer.py
sql_rewriter/_generated/HiveParser.py
sql_rewriter/_generated/HiveParserListener.py
sql_rewriter/_generated/HiveParserVisitor.py
sql_rewriter/_generated/__init__.py
sql_rewriter-0.1.2.dist-info/licenses/LICENSE
sql_rewriter-0.1.2.dist-info/METADATA
sql_rewriter-0.1.2.dist-info/WHEEL
sql_rewriter-0.1.2.dist-info/top_level.txt
sql_rewriter-0.1.2.dist-info/RECORD
