Metadata-Version: 2.4
Name: sql-rewriter
Version: 0.1.2
Summary: ANTLR4-based SQL rewriting tool for permission management in LLM-generated SQL
Author-email: wangyang <wangyang377@ustc.edu>
Maintainer-email: wangyang <wangyang377@ustc.edu>
License: MIT
Project-URL: Homepage, https://github.com/wangyang377/sql-rewriter
Project-URL: Documentation, https://github.com/wangyang377/sql-rewriter#readme
Project-URL: Repository, https://github.com/wangyang377/sql-rewriter
Project-URL: Issues, https://github.com/wangyang377/sql-rewriter/issues
Keywords: sql,rewriter,llm,antlr4,sql-parser,sql-rewrite,hive
Classifier: Development Status :: 3 - Alpha
Classifier: Intended Audience :: Developers
Classifier: Topic :: Software Development :: Libraries :: Python Modules
Classifier: Topic :: Database
Classifier: License :: OSI Approved :: MIT License
Classifier: Programming Language :: Python :: 3
Classifier: Programming Language :: Python :: 3.7
Classifier: Programming Language :: Python :: 3.8
Classifier: Programming Language :: Python :: 3.9
Classifier: Programming Language :: Python :: 3.10
Classifier: Programming Language :: Python :: 3.11
Classifier: Programming Language :: Python :: 3.12
Requires-Python: >=3.7
License-File: LICENSE
Requires-Dist: antlr4-python3-runtime<5.0.0,>=4.13.1
Provides-Extra: dev
Requires-Dist: pytest>=7.0.0; extra == "dev"
Requires-Dist: pytest-cov>=4.0.0; extra == "dev"
Requires-Dist: black>=23.0.0; extra == "dev"
Requires-Dist: ruff>=0.1.0; extra == "dev"
Requires-Dist: mypy>=1.0.0; extra == "dev"
Dynamic: license-file
